Metadata-Version: 2.1
Name: statistica-distributions
Version: 0.1
Summary: Gaussian and Binomial distributions
Home-page: UNKNOWN
Author: Jonathan Koefman
Author-email: jkoefman@outlook.com
License: UNKNOWN
Platform: UNKNOWN
